odoo/addons/shopfloor_full_location_reservation/README.rst
odoo/addons/shopfloor_full_location_reservation/__init__.py
odoo/addons/shopfloor_full_location_reservation/__manifest__.py
odoo/addons/shopfloor_full_location_reservation/hooks.py
odoo/addons/shopfloor_full_location_reservation/i18n/it.po
odoo/addons/shopfloor_full_location_reservation/i18n/shopfloor_full_location_reservation.pot
odoo/addons/shopfloor_full_location_reservation/models/__init__.py
odoo/addons/shopfloor_full_location_reservation/models/shopfloor_menu.py
odoo/addons/shopfloor_full_location_reservation/readme/CONTRIBUTORS.rst
odoo/addons/shopfloor_full_location_reservation/readme/DESCRIPTION.rst
odoo/addons/shopfloor_full_location_reservation/services/__init__.py
odoo/addons/shopfloor_full_location_reservation/services/location_content_transfer.py
odoo/addons/shopfloor_full_location_reservation/services/zone_picking.py
odoo/addons/shopfloor_full_location_reservation/static/description/icon.png
odoo/addons/shopfloor_full_location_reservation/static/description/index.html
odoo/addons/shopfloor_full_location_reservation/tests/__init__.py
odoo/addons/shopfloor_full_location_reservation/tests/test_shopfloor_scenario.py
odoo/addons/shopfloor_full_location_reservation/views/shopfloor_menu.xml
odoo14_addon_shopfloor_full_location_reservation-14.0.1.0.1.dev4.dist-info/METADATA
odoo14_addon_shopfloor_full_location_reservation-14.0.1.0.1.dev4.dist-info/WHEEL
odoo14_addon_shopfloor_full_location_reservation-14.0.1.0.1.dev4.dist-info/top_level.txt
odoo14_addon_shopfloor_full_location_reservation-14.0.1.0.1.dev4.dist-info/RECORD
