Metadata-Version: 2.1
Name: odoo14-addon-shopfloor_full_location_reservation
Version: 14.0.1.0.1.dev4
Summary: Adds a configuration to the shopfloor scenario which allows to trigger the stock full location reservation
Home-page: https://github.com/OCA/wms
Author: MT Software, Odoo Community Association (OCA)
Author-email: support@odoo-community.org
License: AGPL-3
Classifier: Programming Language :: Python
Classifier: Framework :: Odoo
Classifier: Framework :: Odoo :: 14.0
Classifier: License :: OSI Approved :: GNU Affero General Public License v3
Requires-Python: >=3.6
Requires-Dist: odoo14-addon-shopfloor
Requires-Dist: odoo14-addon-stock-full-location-reservation
Requires-Dist: odoo<14.1dev,>=14.0a
